yesterday_cli/__init__.py
yesterday_cli/_version.py
yesterday_cli/main.py
yesterday_cli-0.1.1.dist-info/METADATA
yesterday_cli-0.1.1.dist-info/WHEEL
yesterday_cli-0.1.1.dist-info/entry_points.txt
yesterday_cli-0.1.1.dist-info/top_level.txt
yesterday_cli-0.1.1.dist-info/RECORD
