Metadata-Version: 2.4
Name: yesterday-cli
Version: 0.1.1
Summary: `yesterday` is a tiny Python CLI tool that tells you what day was yesterday. Nothing more. Nothing less.
Author-email: Ilya Khrustalev <ilya.khrustalev@gmail.com>
Requires-Python: >=3.12
